numeric_version/__init__.py
numeric_version/version.py
numeric_version-1.0.3.dist-info/DESCRIPTION.rst
numeric_version-1.0.3.dist-info/METADATA
numeric_version-1.0.3.dist-info/RECORD
numeric_version-1.0.3.dist-info/WHEEL
numeric_version-1.0.3.dist-info/metadata.json
numeric_version-1.0.3.dist-info/top_level.txt
