Metadata-Version: 2.0
Name: numeric-version
Version: 1.0.3
Summary: Very simple module with a numeric version class
Home-page: https://github.com/nicholasbishop/numeric_version
Author: Nicholas Bishop
Author-email: nicholasbishop@gmail.com
License: Apache 2.0
Platform: UNKNOWN
